{
  "yourTokenIs": "Your token is: ",
  "frontPage": "Front page",
  "hello": "Hello,",
  "map": "Map",
  "from": "From",
  "to": "To",
  "findRoute": "Find route",
  "saveRoute": "Save route",
  "savedRoutes": "Saved routes",
  "savedRoutesFrom": "From",
  "savedRoutesTo": "To",
  "savedRoutesSavedText": "Saved",
  "deleteConfirm": "Are you sure you want to delete this?",
  "yes": "Yes",
  "statistics": "Statistics",
  "pollutantPM25": "PM25",
  "pollutantPM10": "PM10",
  "pollutantOzone": "Ozone",
  "pollutantNitrogen": "Nitrogen dioxine",
  "pollutanSulfur": "Sulfur dioxine",
  "cancel": "cancel",
  "confirmTimeRange": "Confirm time range",
  "selectPollution": "Select pollution",
  "reset": "reset",
  "weeklyExposure": "Weekly exposure",
  "monthlyExposure": "Monthly exposure",
  "annualExposure": "Annual exposure",
  "displayTables": "Select time to display tables",
  "selectTime": "Select time",
  "settings": "Settings",
  "airQualityMode": "Air quality mode",
  "movementOptions": "Movement options",
  "walking": "Walking",
  "wheelerchair": "Wheelerchair",
  "homeAddress": "Home address",
  "streetAddress": "Street address",
  "city": "City",
  "zipCode": "Zip code",
  "country": "Country",
  "applyChanges": "Apply changes",
  "downloadData": "Download your data",
  "changeUserData": "Change account settings",
  "deleteAccount": "Delete account",
  "deleteAccountDialogTitle": "Are you sure you want to delete your account?",
  "deleteAccountDialogText": "If you press yes your account can't be recovered. You will be redirected to login page.",
  "viewRoute": "View route",
  "deleteRoute": "Delete route",
  "collapseMenuText": "Collapse menu",
  "user": "User",
  "postalCode": "Postal code",
  "confirmButtonText": "Confirmed",
  "locationNotFoundDialogText": "Location not found"
}